intellithing/__init__.py
intellithing/autotrainer.py
intellithing/hyper_tuner.py
intellithing/layer_freezer.py
intellithing/lr_finder.py
intellithing/t5customdataset.py
intellithing-0.10.dist-info/LICENSE
intellithing-0.10.dist-info/METADATA
intellithing-0.10.dist-info/WHEEL
intellithing-0.10.dist-info/top_level.txt
intellithing-0.10.dist-info/RECORD
